naijaligo_asr/__init__.py
naijaligo_asr/audio.py
naijaligo_asr/cli.py
naijaligo_asr/engine.py
naijaligo_asr/logging_utils.py
naijaligo_asr/registry.py
naijaligo_asr/transcriber.py
naijaligo_asr-0.1.0.dist-info/METADATA
naijaligo_asr-0.1.0.dist-info/WHEEL
naijaligo_asr-0.1.0.dist-info/entry_points.txt
naijaligo_asr-0.1.0.dist-info/top_level.txt
naijaligo_asr-0.1.0.dist-info/RECORD
