Metadata-Version: 2.4
Name: naijaligo-asr
Version: 0.1.0
Summary: ASR SDK for Nigerian languages Yoruba, Igbo, Hausa and Nigerian-accented English using CTranslate2-converted Whisper models
Author: NaijaLingo
License: MIT
Requires-Python: >=3.9
Requires-Dist: faster-whisper>=1.2.0
Requires-Dist: ctranslate2>=4.6.0
Requires-Dist: librosa>=0.11.0
Requires-Dist: numpy>=1.23
